griseo/__init__.py
griseo/__main__.py
griseo/prompts/__init__.py
griseo/prompts/default.jsonl
griseo-0.13.3.dist-info/LICENSE
griseo-0.13.3.dist-info/METADATA
griseo-0.13.3.dist-info/WHEEL
griseo-0.13.3.dist-info/entry_points.txt
griseo-0.13.3.dist-info/RECORD
