Metadata-Version: 2.1
Name: griseo
Version: 0.13.3
Summary: Chat with OpenAI in the Hacker way.
Home-page: https://github.com/korandoru/griseo
License: Apache-2.0
Keywords: chatgpt,cli,openai
Author: tison
Author-email: wander4096@gmail.com
Requires-Python: >=3.8,<4.0
Classifier: License :: OSI Approved :: Apache Software License
Classifier: Programming Language :: Python :: 3
Classifier: Programming Language :: Python :: 3.8
Classifier: Programming Language :: Python :: 3.9
Classifier: Programming Language :: Python :: 3.10
Classifier: Programming Language :: Python :: 3.11
Requires-Dist: importlib-resources (>=5.12.0,<6.0.0)
Requires-Dist: openai (>=0.27.7,<0.28.0)
Requires-Dist: prompt-toolkit (>=3.0.38,<4.0.0)
Requires-Dist: python-dotenv (>=1.0.0,<2.0.0)
Requires-Dist: tenacity (>=8.2.2,<9.0.0)
Project-URL: Documentation, https://github.com/korandoru/griseo
Project-URL: Repository, https://github.com/korandoru/griseo
